<?xml version="1.0" encoding="utf-8" ?>
<!--
========================================================================
   Copyright (c) 2019 Qualcomm Technologies, Inc.
   All Rights Reserved.
   Confidential and Proprietary - Qualcomm Technologies, Inc.
========================================================================
-->
<gamma15_ipe
  xmlns:xsi="http://www.w3.org/2001/XMLSchema-instance"
  xsi:noNamespaceSchemaLocation="..\..\..\..\..\..\..\..\..\..\..\..\..\api\chromatix\XSD\isp\gamma_1_5_0.xsd">
  <enable_section>
    <gamma_enable>1</gamma_enable>
  </enable_section>
  <module_version major_revision="1" minor_revision="5" incr_revision="0"/>
  <parameter_version>
    <revision>0</revision>
  </parameter_version>
  <control_variables>
    <control_var_type>control_drc_gain</control_var_type>
    <control_var_type>control_aec_exp_sensitivity_ratio</control_var_type>
    <control_var_type>control_led_idx</control_var_type>
    <control_var_type>control_lux_idx</control_var_type>
    <control_var_type>control_cct</control_var_type>
  </control_variables>
  <control_method>
    <aec_exp_control>control_lux_idx</aec_exp_control>
    <aec_hdr_control>control_aec_exp_sensitivity_ratio</aec_hdr_control>
  </control_method>
  <private_information>
    <led_sensitivity_trigger>
      <start>1</start>
      <end>100</end>
    </led_sensitivity_trigger>
  </private_information>
  <chromatix_gamma15_core>
    <mod_gamma15_drc_gain_data>
      <drc_gain_trigger>
        <start>1</start>
        <end>100</end>
      </drc_gain_trigger>
      <drc_gain_data>
        <mod_gamma15_hdr_aec_data>
          <hdr_aec_trigger>
            <exp_time_start>1</exp_time_start>
            <exp_time_end>64</exp_time_end>
            <aec_sensitivity_start>1</aec_sensitivity_start>
            <aec_sensitivity_end>64</aec_sensitivity_end>
            <exp_gain_start>1</exp_gain_start>
            <exp_gain_end>64</exp_gain_end>
          </hdr_aec_trigger>
          <hdr_aec_data>
            <mod_gamma15_led_idx_data>
              <led_idx_trigger>0</led_idx_trigger>
              <led_idx_data>
                <mod_gamma15_aec_data>
                  <aec_trigger>
                    <lux_idx_start>1</lux_idx_start>
                    <lux_idx_end>900</lux_idx_end>
                    <gain_start>1</gain_start>
                    <gain_end>200</gain_end>
                  </aec_trigger>
                  <aec_data>
                    <mod_gamma15_cct_data>
                      <cct_trigger>
                        <start>1</start>
                        <end>10000</end>
                      </cct_trigger>
                      <cct_data>
                        <mod_gamma15_channel_data>
                          <!--Channel type selection for R/G/B/All -->
                          <channel_type>channel_R</channel_type>
                          <gamma15_rgn_data type="int" range="[0,1023]" length="257">
                            <table>0 0 0 0 0 0 0 0 0 0 0 0 0 0 0 0 0 0 0 0 0 4 8 16 24 32 40 48 56 68 80 92 104 116 132 144 160 172 188 204 224 240 256 276 292 312 332 352 368 388 408 428 448 464 484 500 520 536 556 572 588 604 620 636 652 664 680 696 708 720 732 744 756 768 776 788 800 808 820 828 836 840 848 860 864 872 880 888 892 900 904 912 916 924 928 932 940 940 944 948 956 960 964 968 972 976 980 980 984 984 988 992 996 996 1000 1000 1004 1008 1008 1008 1012 1016 1016 1016 1020 1020 1020 1020 1023 1023 1023 1023 1023 1023 1023 1023 1023 1023 1023 1023 1023 1023 1023 1023 1023 1023 1023 1023 1023 1023 1023 1023 1023 1023 1023 1023 1023 1023 1023 1023 1023 1023 1023 1023 1023 1023 1023 1023 1023 1023 1023 1023 1023 1023 1023 1023 1023 1023 1023 1023 1023 1023 1023 1023 1023 1023 1023 1023 1023 1023 1023 1023 1023 1023 1023 1023 1023 1023 1023 1023 1023 1023 1023 1023 1023 1023 1023 1023 1023 1023 1023 1023 1023 1023 1023 1023 1023 1023 1023 1023 1023 1023 1023 1023 1023 1023 1023 1023 1023 1023 1023 1023 1023 1023 1023 1023 1023 1023 1023 1023 1023 1023 1023 1023 1023 1023 1023 1023 1023 1023 1023 1023 1023 1023 1023 1023 1023</table>
                          </gamma15_rgn_data>
                        </mod_gamma15_channel_data>
                        <mod_gamma15_channel_data>
                          <!--Channel type selection for R/G/B/All -->
                          <channel_type>channel_G</channel_type>
                          <gamma15_rgn_data type="int" range="[0,1023]" length="257">
                            <table>0 0 0 0 0 0 0 0 0 0 0 0 0 0 0 0 0 0 0 0 0 4 8 16 24 32 40 48 56 68 80 92 104 116 132 144 160 172 188 204 224 240 256 276 292 312 332 352 368 388 408 428 448 464 484 500 520 536 556 572 588 604 620 636 652 664 680 696 708 720 732 744 756 768 776 788 800 808 820 828 836 840 848 860 864 872 880 888 892 900 904 912 916 924 928 932 940 940 944 948 956 960 964 968 972 976 980 980 984 984 988 992 996 996 1000 1000 1004 1008 1008 1008 1012 1016 1016 1016 1020 1020 1020 1020 1023 1023 1023 1023 1023 1023 1023 1023 1023 1023 1023 1023 1023 1023 1023 1023 1023 1023 1023 1023 1023 1023 1023 1023 1023 1023 1023 1023 1023 1023 1023 1023 1023 1023 1023 1023 1023 1023 1023 1023 1023 1023 1023 1023 1023 1023 1023 1023 1023 1023 1023 1023 1023 1023 1023 1023 1023 1023 1023 1023 1023 1023 1023 1023 1023 1023 1023 1023 1023 1023 1023 1023 1023 1023 1023 1023 1023 1023 1023 1023 1023 1023 1023 1023 1023 1023 1023 1023 1023 1023 1023 1023 1023 1023 1023 1023 1023 1023 1023 1023 1023 1023 1023 1023 1023 1023 1023 1023 1023 1023 1023 1023 1023 1023 1023 1023 1023 1023 1023 1023 1023 1023 1023 1023 1023 1023 1023 1023 1023</table>
                          </gamma15_rgn_data>
                        </mod_gamma15_channel_data>
                        <mod_gamma15_channel_data>
                          <!--Channel type selection for R/G/B/All -->
                          <channel_type>channel_B</channel_type>
                          <gamma15_rgn_data type="int" range="[0,1023]" length="257">
                            <table>0 0 0 0 0 0 0 0 0 0 0 0 0 0 0 0 0 0 0 0 0 4 8 16 24 32 40 48 56 68 80 92 104 116 132 144 160 172 188 204 224 240 256 276 292 312 332 352 368 388 408 428 448 464 484 500 520 536 556 572 588 604 620 636 652 664 680 696 708 720 732 744 756 768 776 788 800 808 820 828 836 840 848 860 864 872 880 888 892 900 904 912 916 924 928 932 940 940 944 948 956 960 964 968 972 976 980 980 984 984 988 992 996 996 1000 1000 1004 1008 1008 1008 1012 1016 1016 1016 1020 1020 1020 1020 1023 1023 1023 1023 1023 1023 1023 1023 1023 1023 1023 1023 1023 1023 1023 1023 1023 1023 1023 1023 1023 1023 1023 1023 1023 1023 1023 1023 1023 1023 1023 1023 1023 1023 1023 1023 1023 1023 1023 1023 1023 1023 1023 1023 1023 1023 1023 1023 1023 1023 1023 1023 1023 1023 1023 1023 1023 1023 1023 1023 1023 1023 1023 1023 1023 1023 1023 1023 1023 1023 1023 1023 1023 1023 1023 1023 1023 1023 1023 1023 1023 1023 1023 1023 1023 1023 1023 1023 1023 1023 1023 1023 1023 1023 1023 1023 1023 1023 1023 1023 1023 1023 1023 1023 1023 1023 1023 1023 1023 1023 1023 1023 1023 1023 1023 1023 1023 1023 1023 1023 1023 1023 1023 1023 1023 1023 1023 1023 1023</table>
                          </gamma15_rgn_data>
                        </mod_gamma15_channel_data>
                      </cct_data>
                    </mod_gamma15_cct_data>
                  </aec_data>
                </mod_gamma15_aec_data>
              </led_idx_data>
            </mod_gamma15_led_idx_data>
          </hdr_aec_data>
        </mod_gamma15_hdr_aec_data>
      </drc_gain_data>
    </mod_gamma15_drc_gain_data>
  </chromatix_gamma15_core>
</gamma15_ipe>
